attendance/__init__.py
attendance/admin.py
attendance/apps.py
attendance/forms.py
attendance/models.py
attendance/tests.py
attendance/urls.py
attendance/utils.py
attendance/views.py
attendance/migrations/0001_initial.py
attendance/migrations/0002_alter_attendance_time_am_alter_attendance_time_pm.py
attendance/migrations/0003_alter_attendance_time_am_alter_attendance_time_pm.py
attendance/migrations/0004_alter_attendance_is_present_attendancetotal.py
attendance/migrations/0005_attendance_month_attendance_year.py
attendance/migrations/0006_alter_attendancetotal_month_and_more.py
attendance/migrations/0007_alter_attendance_is_present.py
attendance/migrations/0008_alter_attendanceunit_month_alter_attendanceunit_year.py
attendance/migrations/0009_attendancetotal_unit.py
attendance/migrations/0010_alter_attendanceunit_file.py
attendance/migrations/0011_auto_20221208_1056.py
attendance/migrations/0012_auto_20221208_1251.py
attendance/migrations/0013_auto_20221208_1313.py
attendance/migrations/0014_attendance_leader.py
attendance/migrations/0015_auto_20221209_1536.py
attendance/migrations/0016_auto_20221210_2258.py
attendance/migrations/0017_auto_20221212_1502.py
attendance/migrations/0018_alter_attendance_totat_hour.py
attendance/migrations/0019_attendance_is_hr_update.py
attendance/migrations/0020_alter_attendance_is_hr_update.py
attendance/migrations/0021_auto_20230215_1923.py
attendance/migrations/__init__.py
attendance/migrations/__pycache__/0001_initial.cpython-310.pyc
attendance/migrations/__pycache__/0001_initial.cpython-37.pyc
attendance/migrations/__pycache__/0001_initial.cpython-39.pyc
attendance/migrations/__pycache__/0002_alter_attendance_time_am_alter_attendance_time_pm.cpython-310.pyc
attendance/migrations/__pycache__/0002_alter_attendance_time_am_alter_attendance_time_pm.cpython-37.pyc
attendance/migrations/__pycache__/0002_alter_attendance_time_am_alter_attendance_time_pm.cpython-39.pyc
django_ipghrms_attendance-1.8.dist-info/LICENSE
django_ipghrms_attendance-1.8.dist-info/METADATA
django_ipghrms_attendance-1.8.dist-info/WHEEL
django_ipghrms_attendance-1.8.dist-info/top_level.txt
django_ipghrms_attendance-1.8.dist-info/RECORD
